{
  "project_info": {
    "project_number": "830199449953",
    "project_id": "uesiap-aaf9c",
    "storage_bucket": "uesiap-aaf9c.appspot.com"
  },
  "client": [
    {
      "client_info": {
        "mobilesdk_app_id": "1:830199449953:android:0b7079c612b4a099ef5d20",
        "android_client_info": {
          "package_name": "com.uesiap.geethavali"
        }
      },
      "oauth_client": [
        {
          "client_id": "830199449953-d3tnrd8maaoo498j9tld4a6smuv80vlt.apps.googleusercontent.com",
          "client_type": 1,
          "android_info": {
            "package_name": "com.uesiap.geethavali",
            "certificate_hash": "57d7e70d74d6ed7673c6cfc2d143002fe3b145db"
          }
        },
        {
          "client_id": "830199449953-pv0p8ume9tnjucc1r2elb6mpv0tql9h6.apps.googleusercontent.com",
          "client_type": 1,
          "android_info": {
            "package_name": "com.uesiap.geethavali",
            "certificate_hash": "25003a556475036c484e762ac5c0da42db68a224"
          }
        },
        {
          "client_id": "830199449953-868ttsrt7fvo94hkkr6he6aidqb6j429.apps.googleusercontent.com",
          "client_type": 3
        }
      ],
      "api_key": [
        {
          "current_key": "AIzaSyAUb7ySoktJyG2Ci1Pm3ZWTLDJR-tMtBVg"
        }
      ],
      "services": {
        "appinvite_service": {
          "other_platform_oauth_client": [
            {
              "client_id": "830199449953-868ttsrt7fvo94hkkr6he6aidqb6j429.apps.googleusercontent.com",
              "client_type": 3
            }
          ]
        }
      }
    }
  ],
  "configuration_version": "1"
}